qck_pyiseasy/__init__.py
qck_pyiseasy/main.py
qck_pyiseasy-0.0.2.dist-info/LICENSE
qck_pyiseasy-0.0.2.dist-info/METADATA
qck_pyiseasy-0.0.2.dist-info/WHEEL
qck_pyiseasy-0.0.2.dist-info/top_level.txt
qck_pyiseasy-0.0.2.dist-info/RECORD
