Metadata-Version: 2.1
Name: qck-pyiseasy
Version: 0.0.2
Summary: Make python easy AF
Home-page: https://github.com/Tarvey/pyISeasy
Author: tarqak
Author-email: quaqek@gmail.com
Project-URL: Bug Tracker, https://github.com/Tarvey/pyISeasy/issues
Classifier: Programming Language :: Python :: 3
Classifier: License :: OSI Approved :: MIT License
Classifier: Operating System :: OS Independent
Requires-Python: >=3.6
License-File: LICENSE
